mysql_table_model/__init__.py
mysql_table_model/semikron.py
mysql_table_model-0.1.4.dist-info/METADATA
mysql_table_model-0.1.4.dist-info/WHEEL
mysql_table_model-0.1.4.dist-info/RECORD
