Metadata-Version: 2.1
Name: mysql-table-model
Version: 0.1.4
Summary: CYG 本地MES数据表模型
Author: LiuWei
Author-email: 183074632@qq.com
Requires-Python: >=3.11,<4.0
Classifier: Programming Language :: Python :: 3
Classifier: Programming Language :: Python :: 3.11
Classifier: Programming Language :: Python :: 3.12
Classifier: Programming Language :: Python :: 3.13
Requires-Dist: mysql-api (>=0.1.2,<0.2.0)
Requires-Dist: sqlalchemy (>=2.0.36,<3.0.0)
